MANIFEST.in
README.md
setup.py
django_trending.egg-info/PKG-INFO
django_trending.egg-info/SOURCES.txt
django_trending.egg-info/dependency_links.txt
django_trending.egg-info/not-zip-safe
django_trending.egg-info/top_level.txt
trending/__init__.py
trending/admin.py
trending/managers.py
trending/models.py